starrail_damage_cal-3.8.0.dist-info/METADATA
starrail_damage_cal-3.8.0.dist-info/WHEEL
starrail_damage_cal-3.8.0.dist-info/entry_points.txt
starrail_damage_cal-3.8.0.dist-info/licenses/LICENSE
starrail_damage_cal/__init__.py
starrail_damage_cal/cal_damage.py
starrail_damage_cal/damage/Avatar.py
starrail_damage_cal/damage/AvatarDamage/AvatarDamage.py
starrail_damage_cal/damage/AvatarDamage/__init__.py
starrail_damage_cal/damage/Base/AvatarBase.py
starrail_damage_cal/damage/Base/RelicBase.py
starrail_damage_cal/damage/Base/SkillBase.py
starrail_damage_cal/damage/Base/WeaponBase.py
starrail_damage_cal/damage/Base/__init__.py
starrail_damage_cal/damage/Base/model.py
starrail_damage_cal/damage/Excel/SkillData.json
starrail_damage_cal/damage/Excel/weapon_effect.json
starrail_damage_cal/damage/Relic/Relic.py
starrail_damage_cal/damage/Relic/__init__.py
starrail_damage_cal/damage/Role.py
starrail_damage_cal/damage/Weapon/Weapon.py
starrail_damage_cal/damage/Weapon/__init__.py
starrail_damage_cal/damage/__init__.py
starrail_damage_cal/damage/utils.py
starrail_damage_cal/excel/AvatarPromotionConfig.json
starrail_damage_cal/excel/AvatarPromotionConfigLD.json
starrail_damage_cal/excel/AvatarRelicScore.json
starrail_damage_cal/excel/EquipmentPromotionConfig.json
starrail_damage_cal/excel/RelicMainAffixConfig.json
starrail_damage_cal/excel/RelicSubAffixConfig.json
starrail_damage_cal/excel/__init__.py
starrail_damage_cal/excel/char_alias.json
starrail_damage_cal/excel/model.py
starrail_damage_cal/excel/relic_scores.json
starrail_damage_cal/exception.py
starrail_damage_cal/logger.py
starrail_damage_cal/map/SR_MAP_PATH.py
starrail_damage_cal/map/__init__.py
starrail_damage_cal/map/data/EquipmentID2AbilityProperty_mapping.json
starrail_damage_cal/map/data/EquipmentID2EnName_mapping.json
starrail_damage_cal/map/data/EquipmentID2Name_mapping.json
starrail_damage_cal/map/data/EquipmentID2Rarity_mapping.json
starrail_damage_cal/map/data/ItemId2Name_mapping.json
starrail_damage_cal/map/data/Property2Name_mapping.json
starrail_damage_cal/map/data/RelicId2MainAffixGroup_mapping.json
starrail_damage_cal/map/data/RelicId2Rarity_mapping.json
starrail_damage_cal-3.8.0.dist-info/RECORD
