Metadata-Version: 2.1
Name: starrail_damage_cal
Version: 3.8.0
Summary: For StarRail Role Damage Cal
Author-Email: qwerdvd <105906879+qwerdvd@users.noreply.github.com>, ilnli <220916405+ilnli@users.noreply.github.com>
License: MIT
Requires-Python: >=3.9
Requires-Dist: msgspec>=0.18.6
Requires-Dist: httpx>=0.27.0
Requires-Dist: aiohttp>=3.11.11
